onRobot/__init_.py
onRobot/gripper.py
onRobot-0.1.0.dist-info/METADATA
onRobot-0.1.0.dist-info/WHEEL
onRobot-0.1.0.dist-info/top_level.txt
onRobot-0.1.0.dist-info/RECORD
